mlde_utils/__init__.py
mlde_utils/transforms.py
mlde_utils/data/__init__.py
mlde_utils/data/coarsen.py
mlde_utils/data/constrain.py
mlde_utils/data/diff.py
mlde_utils/data/regrid.py
mlde_utils/data/remapcon.py
mlde_utils/data/resample.py
mlde_utils/data/select_domain.py
mlde_utils/data/select_gcm_domain.py
mlde_utils/data/shift_lon_break.py
mlde_utils/data/split_by_year.py
mlde_utils/data/sum.py
mlde_utils/data/vorticity.py
mlde_utils/data/target_grids/2.2km/uk/moose_grid.nc
mlde_utils/data/target_grids/2.2km-coarsened-27x/uk/moose_grid.nc
mlde_utils/data/target_grids/2.2km-coarsened-2x/uk/moose_grid.nc
mlde_utils/data/target_grids/2.2km-coarsened-4x/uk/moose_grid.nc
mlde_utils/data/target_grids/2.2km-coarsened-8x/uk/moose_grid.nc
mlde_utils/data/target_grids/60km/global/pr/moose_grid.nc
mlde_utils/data/target_grids/60km/global/vorticity850/moose_grid.nc
mlde_utils/training/__init__.py
mlde_utils/training/dataset.py
mlde_utils-0.2.5.dist-info/licenses/LICENSE
mlde_utils-0.2.5.dist-info/METADATA
mlde_utils-0.2.5.dist-info/WHEEL
mlde_utils-0.2.5.dist-info/top_level.txt
mlde_utils-0.2.5.dist-info/RECORD
