Metadata-Version: 2.4
Name: mlde_utils
Version: 0.2.5
Summary: A package for shared code between ML downscaling repos
Author-email: Henry Addison <henry.addison@bristol.ac.uk>
Project-URL: Homepage, https://github.com/henryaddison/mlde_utils
Project-URL: Bug Tracker, https://github.com/henryaddison/mlde_utils/issues
Classifier: Programming Language :: Python :: 3
Classifier: License :: OSI Approved :: MIT License
Classifier: Operating System :: OS Independent
Requires-Python: >=3.7
License-File: LICENSE
Requires-Dist: cf-xarray
Dynamic: license-file
